[
  {
    "global": 12.89,
    "lines_valid": 9070,
    "lines_covered": 1460,
    "packages": {
      ".": 72.27000000000001,
      "agents": 45.0,
      "agents.core": 35.0,
      "agents.core.extract": 14.869999999999997,
      "agents.core.informal": 11.23,
      "agents.core.pl": 16.51,
      "agents.core.pm": 37.11,
      "agents.extract": 57.5,
      "agents.runners": 95.0,
      "agents.runners.test": 95.0,
      "agents.runners.test.informal": 17.220000000000002,
      "agents.runners.test.orchestration": 95.0,
      "agents.test_scripts": 95.0,
      "agents.test_scripts.informal": 16.48,
      "agents.test_scripts.orchestration": 95.0,
      "agents.tools": 95.0,
      "agents.tools.analysis": 11.46,
      "agents.tools.analysis.enhanced": 7.9,
      "agents.tools.analysis.new": 10.479999999999999,
      "core": 13.709999999999997,
      "core.communication": 13.0,
      "orchestration": 77.05,
      "orchestration.hierarchical": 95.0,
      "orchestration.hierarchical.interfaces": 9.66,
      "orchestration.hierarchical.operational": 16.17,
      "orchestration.hierarchical.operational.adapters": 7.4399999999999995,
      "orchestration.hierarchical.strategic": 9.180000000000001,
      "orchestration.hierarchical.tactical": 6.779999999999999,
      "services": 15.0,
      "ui": 19.560000000000002,
      "utils": 20.86
    },
    "timestamp": "2025-04-20"
  },
  {
    "global": 17.89,
    "lines_valid": 9070,
    "lines_covered": 1623,
    "packages": {
      ".": 77.27000000000001,
      "agents": 50.0,
      "agents.core": 40.0,
      "agents.core.extract": 19.869999999999997,
      "agents.core.informal": 16.23,
      "agents.core.pl": 21.51,
      "agents.core.pm": 42.11,
      "agents.extract": 62.5,
      "agents.runners": 100.0,
      "agents.runners.test": 100.0,
      "agents.runners.test.informal": 22.220000000000002,
      "agents.runners.test.orchestration": 100.0,
      "agents.test_scripts": 100.0,
      "agents.test_scripts.informal": 21.48,
      "agents.test_scripts.orchestration": 100.0,
      "agents.tools": 100.0,
      "agents.tools.analysis": 16.46,
      "agents.tools.analysis.enhanced": 12.9,
      "agents.tools.analysis.new": 15.479999999999999,
      "core": 18.709999999999997,
      "core.communication": 18.0,
      "orchestration": 82.05,
      "orchestration.hierarchical": 100.0,
      "orchestration.hierarchical.interfaces": 14.66,
      "orchestration.hierarchical.operational": 21.17,
      "orchestration.hierarchical.operational.adapters": 12.44,
      "orchestration.hierarchical.strategic": 14.180000000000001,
      "orchestration.hierarchical.tactical": 11.78,
      "services": 20.0,
      "ui": 24.560000000000002,
      "utils": 25.86
    },
    "timestamp": "2025-05-20"
  }
]